pyplearnr/__init__.py
pyplearnr/folds.py
pyplearnr/nested_k_fold_cross_validation.py
pyplearnr/old.py
pyplearnr/pipeline_builder.py
pyplearnr/pipeline_evaluator.py
pyplearnr/trained_pipeline.py
pyplearnr-1.0.11.1.dist-info/DESCRIPTION.rst
pyplearnr-1.0.11.1.dist-info/METADATA
pyplearnr-1.0.11.1.dist-info/RECORD
pyplearnr-1.0.11.1.dist-info/WHEEL
pyplearnr-1.0.11.1.dist-info/metadata.json
pyplearnr-1.0.11.1.dist-info/top_level.txt
test/test_pyplearnr.py
