Metadata-Version: 2.0
Name: pyplearnr
Version: 1.0.11.1
Summary: Pyplearnr is a tool designed to easily and more elegantly build, validate (nested k-fold cross-validation), and test scikit-learn pipelines.
Home-page: http://packages.python.org/pyplearnr
Author: Christopher Shymansky
Author-email: CMShymansky@gmail.com
License: OSI Approved :: Apache Software License
Keywords: scikit-learn pipeline k-fold cross-validation model selection
Platform: UNKNOWN
Classifier: Development Status :: 3 - Alpha
Classifier: Topic :: Utilities
Classifier: License :: OSI Approved :: Apache Software License
Requires-Dist: matplotlib
Requires-Dist: numpy
Requires-Dist: pandas
Requires-Dist: sklearn
